irishgeo/__init__.py
irishgeo/fields.py
irishgeo-0.1.0.dist-info/METADATA
irishgeo-0.1.0.dist-info/WHEEL
irishgeo-0.1.0.dist-info/licenses/LICENSE
irishgeo-0.1.0.dist-info/RECORD
